dot_product/__init__.py
dot_product/dot_product.py
dot_product_beko-1.0.1.dist-info/LICENSE
dot_product_beko-1.0.1.dist-info/METADATA
dot_product_beko-1.0.1.dist-info/WHEEL
dot_product_beko-1.0.1.dist-info/top_level.txt
dot_product_beko-1.0.1.dist-info/RECORD
