Metadata-Version: 2.2
Name: dot_product_beko
Version: 1.0.1
Summary: Fast dot product computation using Assembly (AVX2)
Author: Abdulhamit Güngören
Author-email: Abdulhamit Güngören <abdulhamitgungoren@gmail.com>
License: MIT
Requires-Python: >=3.6
License-File: LICENSE
Requires-Dist: numpy
Dynamic: author
